{
 "info": [
   {
    "package_name":"bestplayer.freeplayer.videoplayer2019",
    "active_ad" : "1",
    "random_no" : "1",
    "fb_advance_native_skippos" : "10",
    "firstpage_fb_duration" : "0",
    "IsAdshowOneTime" : "false",
    "google_ad_interestial": "ca-app-pub-6113069574875874/8036427682",
    "google_banner" : "",
    "fb_ad_interestial" : "801105573567012_801106963566873",
    "fb_ad_interestial_duration" : "800",
    "fb_advance_native_adid" : "801105573567012_801106413566928",
    "fb_nativebanner" : "801105573567012_801107543566815",
    "active_banner_ad" : "1",
    "is_update" : "true",
    "is_forcefully": "false",
    "version_code" : "1",
    "new_version_code" : "1",
    "message" : "Update new 11 Version is available to download. Downlaoding the latest version you will get the latest features,improvements and bug fix version",
    "custom_adurl" : "https://raw.githubusercontent.com/apps-developer2/apps-develop/master/musicbanners.png",
    "customad_pkg" : "org.freemusicplayer.musicplayernew",
    "cust_isshow" : "true"
},
  {
    "package_name":"bestplayer.freeplayer.videoplayer2019",
    "active_ad" : "2",
    "random_no" : "1",
    "fb_advance_native_skippos" : "10",
    "firstpage_fb_duration" : "0",
    "IsAdshowOneTime" : "false",
    "google_ad_interestial": "ca-app-pub-6113069574875874/8036427682",
    "google_banner" : "",
    "fb_ad_interestial" : "801105573567012_801106963566873",
    "fb_ad_interestial_duration" : "800",
    "fb_advance_native_adid" : "801105573567012_801106413566928",
    "fb_nativebanner" : "801105573567012_801107543566815",
    "active_banner_ad" : "2",
    "is_update" : "false",
    "is_forcefully": "false",
    "version_code" : "2",
    "new_version_code" : "2",
    "message" : "Update new 11 Version is available to download. Downlaoding the latest version you will get the latest features,improvements and bug fix version",
    "custom_adurl" : "https://raw.githubusercontent.com/apps-developer2/apps-develop/master/musicbanners.png",
    "customad_pkg" : "org.freemusicplayer.musicplayernew",
    "cust_isshow" : "true"
},
   {
    "package_name":"bestplayer.freeplayer.videoplayer2019",
    "active_ad" : "2",
    "random_no" : "1",
    "fb_advance_native_skippos" : "9",
    "firstpage_fb_duration" : "0",
    "IsAdshowOneTime" : "false",
    "google_ad_interestial": "",
    "google_banner" : "",
    "google_native_appid" : "",
    "google_native_adid" : "",
    "is_nativeadvance_active" : "2",
    "fb_ad_interestial" : "",
    "fb_ad_interestial_duration" : "800",
    "fb_advance_native_adid" : "",
    "fb_nativebanner" : "",
    "active_banner_ad" : "1",
    "is_fb_bannerad_show" : "2",
    "is_update" : "true",
    "is_forcefully": "true",
    "is_live" : "false",
    "new_url" : "https://play.google.com/store/apps/details?id=video.hdvideo.videoplayer",
    "version_code" : "3",
    "new_version_code" : "3",
    "message" : "Update new 4 Version is available to download. Downlaoding the latest version you will get the latest features,improvements and bug fix version",
    "custom_adurl" : "https://raw.githubusercontent.com/apps-developer/common-ad-setting/master/gallerybanner.png",
    "customad_pkg" : "galleryapps.galleryalbum.gallery",
    "cust_isshow" : "true",
    "notiappname" : "ADvance HD Gallery",
    "notidesc" : "Advance Gallery is best HD Photo Gallery 2019",
    "notiurl" : "",
    "notipkg" : "galleryapps.galleryalbum.gallery2019"
},
   {
    "package_name":"bestplayer.freeplayer.videoplayer2019",
    "active_ad" : "1",
    "random_no" : "1",
    "fb_advance_native_skippos" : "20",
    "firstpage_fb_duration" : "0",
    "IsAdshowOneTime" : "false",
    "google_ad_interestial": "",
    "google_banner" : "",
    "google_native_appid" : "",
    "google_native_adid" : "",
    "is_nativeadvance_active" : "2",
    "fb_ad_interestial" : "",
    "fb_ad_interestial_duration" : "800",
    "fb_advance_native_adid" : "",
    "fb_nativebanner" : "",
    "active_banner_ad" : "1",
    "is_fb_bannerad_show" : "2",
    "is_update" : "true",
    "is_forcefully": "true",
    "is_live" : "false",
    "new_url" : "https://play.google.com/store/apps/details?id=video.hdvideo.videoplayer",
    "version_code" : "4",
    "new_version_code" : "4",
    "message" : "Update new 5 Version is available to download. Downlaoding the latest version you will get the latest features,improvements and bug fix version",
    "custom_adurl" : "https://raw.githubusercontent.com/apps-developer/common-ad-setting/master/gallerybanner.png",
    "customad_pkg" : "galleryapps.galleryalbum.gallery",
    "cust_isshow" : "true",
    "notiappname" : "Music Player 2019",
    "notidesc" : "Music Player with powerful equalizer, Quick search all your music files",
    "notiurl" : "",
    "notipkg" : "music.player.musicplayernew"
}
]
}
